{
  "app:toggle-left-sidebar": [
    {
      "modifiers": [
        "Mod"
      ],
      "key": "["
    }
  ],
  "app:toggle-right-sidebar": [
    {
      "modifiers": [
        "Mod"
      ],
      "key": "]"
    }
  ],
  "obsidian-kanban:toggle-kanban-view": [
    {
      "modifiers": [
        "Mod"
      ],
      "key": "M"
    }
  ],
  "editor:focus-top": [
    {
      "modifiers": [
        "Alt",
        "Mod"
      ],
      "key": "K"
    }
  ],
  "editor:focus-bottom": [
    {
      "modifiers": [
        "Alt",
        "Mod"
      ],
      "key": "J"
    }
  ],
  "editor:focus-left": [
    {
      "modifiers": [
        "Alt",
        "Mod"
      ],
      "key": "H"
    }
  ],
  "editor:focus-right": [
    {
      "modifiers": [
        "Alt",
        "Mod"
      ],
      "key": "L"
    }
  ]
}